config.defaults.yaml
scope/__init__.py
scope/_instantiate.py
scope/fritz.py
scope/models.py
scope/nn.py
scope/scope_class.py
scope/utils.py
scope/xgb.py
tools/DNN_AL_mapper.json
tools/XGB_AL_mapper.json
tools/analyze_logs.py
tools/combine_preds.py
tools/combine_preds_slurm.py
tools/featureGeneration/alertstats.py
tools/featureGeneration/external_xmatch.py
tools/featureGeneration/lcstats.py
tools/featureGeneration/periodsearch.py
tools/featureGeneration/pyaov/__init__.py
tools/featureGeneration/pyaov/aov.f90
tools/featureGeneration/pyaov/aovconst.f90
tools/featureGeneration/pyaov/aovsub.f90
tools/featureGeneration/pyaov/build.sh
tools/fritz_mapper.json
tools/generate_features.py
tools/generate_features_job_submission.py
tools/generate_features_slurm.py
tools/get_features.py
tools/get_quad_ids.py
tools/golden_dataset_mapper.json
tools/inference.py
tools/local_scope_radec.csv
tools/local_scope_ztfid.csv
tools/run_inference_job_submission.py
tools/run_inference_slurm.py
tools/run_scope_local.py
tools/scope_download_classification.py
tools/scope_download_gcn_sources.py
tools/scope_manage_annotation.py
tools/scope_upload_classification.py
tools/scope_upload_disagreements.py
tools/taxonomy.py
tools/train_algorithm_job_submission.py
tools/train_algorithm_slurm.py
scope_ml-0.9.5.dist-info/LICENSE
scope_ml-0.9.5.dist-info/METADATA
scope_ml-0.9.5.dist-info/WHEEL
scope_ml-0.9.5.dist-info/entry_points.txt
scope_ml-0.9.5.dist-info/RECORD
